tableau_pdf/__init__.py
tableau_pdf/algorithm/intervalic.py
tableau_pdf-0.0.1.dist-info/WHEEL
tableau_pdf-0.0.1.dist-info/METADATA
tableau_pdf-0.0.1.dist-info/RECORD
